<?xml version="1.0" encoding="UTF-8"?>
<objects serializationModel="Studio.02.03.00">
	<object class="ParameterPreset" id="{a40d93ee-eca4-489f-ba61-d5dc6e34ddc5}">
		<property name="name">
			<value>Enemy Attack</value>
		</property>
		<relationship name="folder">
			<destination>{d2d00e70-f7e4-46c7-ac85-3c2406e406df}</destination>
		</relationship>
		<relationship name="parameter">
			<destination>{125e0333-64e1-4754-9648-6dba2bcc3fc5}</destination>
		</relationship>
	</object>
	<object class="GameParameter" id="{125e0333-64e1-4754-9648-6dba2bcc3fc5}">
		<property name="parameterType">
			<value>2</value>
		</property>
		<property name="maximum">
			<value>4</value>
		</property>
		<property name="enumerationLabels">
			<value>Imp</value>
			<value>Mite</value>
			<value>Spider</value>
			<value>Slug</value>
		</property>
		<property name="initialValue">
			<value>0</value>
		</property>
	</object>
</objects>
